strangeworks_qiskit_runtime/__init__.py
strangeworks_qiskit_runtime/runtime_client.py
strangeworks_qiskit_runtime/service.py
strangeworks_qiskit_runtime/sw_runtime_job.py
strangeworks_qiskit_runtime-0.2.4.dist-info/METADATA
strangeworks_qiskit_runtime-0.2.4.dist-info/WHEEL
strangeworks_qiskit_runtime-0.2.4.dist-info/RECORD
