Metadata-Version: 2.3
Name: strangeworks-qiskit-runtime
Version: 0.2.4
Summary: 
Author: Your Name
Author-email: you@example.com
Requires-Python: >=3.10,<4.0
Classifier: Programming Language :: Python :: 3
Classifier: Programming Language :: Python :: 3.10
Classifier: Programming Language :: Python :: 3.11
Classifier: Programming Language :: Python :: 3.12
Classifier: Programming Language :: Python :: 3.13
Requires-Dist: qiskit-ibm-runtime (==0.39.0)
Requires-Dist: strangeworks (>=0.6.1,<0.7.0)
